vibe_controls/__init__.py
vibe_controls/fly_control.py
vibe_controls-0.1.7.dist-info/licenses/LICENSE
vibe_controls-0.1.7.dist-info/METADATA
vibe_controls-0.1.7.dist-info/WHEEL
vibe_controls-0.1.7.dist-info/entry_points.txt
vibe_controls-0.1.7.dist-info/top_level.txt
vibe_controls-0.1.7.dist-info/RECORD
