Metadata-Version: 2.4
Name: vibe-controls
Version: 0.1.7
Summary: A Python package to control games using hand gestures via webcam. Supports fly, shoot, and flappy modes.
Author-email: VxAI <vxasi7@gmail.com>
License-Expression: MIT
Project-URL: Homepage, https://github.com/VxASI/vibe-play
Classifier: Programming Language :: Python :: 3
Classifier: Operating System :: OS Independent
Requires-Python: <3.12,>=3.7
License-File: LICENSE
Requires-Dist: mediapipe>=0.10.14
Requires-Dist: opencv-python>=4.5.0
Requires-Dist: pynput>=1.7.0
Dynamic: license-file
